statusof/__init__.py
statusof/__main__.py
statusof/statusof.py
statusof-0.2.2.dist-info/METADATA
statusof-0.2.2.dist-info/WHEEL
statusof-0.2.2.dist-info/entry_points.txt
statusof-0.2.2.dist-info/top_level.txt
statusof-0.2.2.dist-info/RECORD
