Metadata-Version: 2.1
Name: statusof
Version: 0.2.2
Summary: Small python script to check the status of a list of urls.
Home-page: https://github.com/arthurdw/statusof
Author: Arthurdw
Author-email: dev@arthurdw.com
License: MIT
Classifier: License :: OSI Approved :: MIT License
Classifier: Programming Language :: Python :: 3
Classifier: Programming Language :: Python :: 3.10
Requires-Dist: aiohttp
Requires-Dist: colorama
